pymatgen/py.typed
pymatgen/dao.py
pymatgen/entries/compatibility.py
pymatgen/entries/MP2020Compatibility.yaml
pymatgen/entries/mixing_scheme.py
pymatgen/entries/computed_entries.py
pymatgen/entries/__init__.py
pymatgen/entries/correction_calculator.py
pymatgen/entries/calc_compounds.json.gz
pymatgen/entries/MPCompatibility.yaml
pymatgen/entries/entry_tools.py
pymatgen/entries/MITCompatibility.yaml
pymatgen/entries/exp_compounds.json.gz
pymatgen/entries/exp_entries.py
pymatgen/entries/data/nist_gas_gf.json
pymatgen/entries/data/g_els.json
pymatgen/core/xcfunc.py
pymatgen/core/periodic_table.py
pymatgen/core/reconstructions_archive.json
pymatgen/core/units.py
pymatgen/core/ion.py
pymatgen/core/libxcfunc.py
pymatgen/core/tensors.py
pymatgen/core/interface.py
pymatgen/core/bond_lengths.json
pymatgen/core/__init__.py
pymatgen/core/trajectory.py
pymatgen/core/operations.py
pymatgen/core/func_groups.json
pymatgen/core/molecular_orbitals.py
pymatgen/core/spectrum.py
pymatgen/core/bonds.py
pymatgen/core/sites.py
pymatgen/core/lattice.py
pymatgen/core/structure.py
pymatgen/core/libxc_docs.json
pymatgen/core/composition.py
pymatgen/core/quad_data.json
pymatgen/core/periodic_table.json.gz
pymatgen/core/surface.py
pymatgen/transformations/standard_transformations.py
pymatgen/transformations/__init__.py
pymatgen/transformations/transformation_abc.py
pymatgen/transformations/advanced_transformations.py
pymatgen/transformations/site_transformations.py
pymatgen/analysis/fragmenter.py
pymatgen/analysis/eos.py
pymatgen/analysis/energy_models.py
pymatgen/analysis/disorder.py
pymatgen/analysis/reaction_calculator.py
pymatgen/analysis/icsd_bv.yaml
pymatgen/analysis/bonds_jmol_ob.yaml
pymatgen/analysis/surface_analysis.py
pymatgen/analysis/ionic_radii.json
pymatgen/analysis/structure_matcher.py
pymatgen/analysis/pourbaix_diagram.py
pymatgen/analysis/costdb_elements.csv
pymatgen/analysis/wulff.py
pymatgen/analysis/local_env.py
pymatgen-2025.10.7.dist-info/RECORD
pymatgen-2025.10.7.dist-info/WHEEL
pymatgen-2025.10.7.dist-info/entry_points.txt
pymatgen-2025.10.7.dist-info/top_level.txt
pymatgen-2025.10.7.dist-info/METADATA
pymatgen-2025.10.7.dist-info/licenses/LICENSE
