Metadata-Version: 2.4
Name: pymatgen
Version: 2025.10.7
Summary: Python Materials Genomics is a robust materials analysis code that defines core object representations for structures
Author-email: Pymatgen Development Team <ongsp@ucsd.edu>
Maintainer-email: Matthew Horton <m.k.horton@gmail.com>, Shyue Ping Ong <ongsp@ucsd.edu>
License: MIT
Project-URL: Homepage, https://pymatgen.org
Project-URL: Documentation, https://pymatgen.org
Project-URL: Repository, https://github.com/materialsproject/pymatgen
Project-URL: Issues, https://github.com/materialsproject/pymatgen/issues
Project-URL: Pypi, https://pypi.org/project/pymatgen
Keywords: ABINIT,VASP,analysis,crystal,diagrams,electronic,gaussian,materials,nwchem,phase,project,qchem,science,structure
Classifier: Development Status :: 4 - Beta
Classifier: Intended Audience :: Science/Research
Classifier: License :: OSI Approved :: MIT License
Classifier: Operating System :: OS Independent
Classifier: Programming Language :: Python :: 3
Classifier: Programming Language :: Python :: 3.10
Classifier: Programming Language :: Python :: 3.11
Classifier: Programming Language :: Python :: 3.12
Classifier: Programming Language :: Python :: 3.13
Classifier: Topic :: Scientific/Engineering :: Chemistry
Classifier: Topic :: Scientific/Engineering :: Information Analysis
Classifier: Topic :: Scientific/Engineering :: Physics
Classifier: Topic :: Software Development :: Libraries :: Python Modules
Requires-Python: >=3.10
License-File: LICENSE
Requires-Dist: bibtexparser>=1.4.0
Requires-Dist: joblib>=1
Requires-Dist: matplotlib>=3.8
Requires-Dist: monty>=2025.1.9
Requires-Dist: networkx>=2.7
Requires-Dist: numpy<3,>=1.25.0
Requires-Dist: orjson<4,>=3.10
Requires-Dist: palettable>=3.3.3
Requires-Dist: pandas>=2
Requires-Dist: plotly>=5.0.0
Requires-Dist: requests>=2.30
Requires-Dist: ruamel.yaml>=0.17.0
Requires-Dist: scipy>=1.13.0
Requires-Dist: scipy>=1.14.1; platform_system == "Windows"
Requires-Dist: spglib>=2.5
Requires-Dist: sympy>=1.3
Requires-Dist: tabulate>=0.9
Requires-Dist: tqdm>=4.60
Requires-Dist: uncertainties>=3.1.4
Provides-Extra: abinit
Requires-Dist: netcdf4>=1.7.2; extra == "abinit"
Provides-Extra: ase
Requires-Dist: ase>=3.23.0; extra == "ase"
Provides-Extra: electronic-structure
Requires-Dist: fdint>=2.0.2; extra == "electronic-structure"
Provides-Extra: matcalc
Requires-Dist: matcalc>=0.4.0; python_version < "3.13" and extra == "matcalc"
Requires-Dist: matgl>=1.2.7; python_version < "3.13" and extra == "matcalc"
Provides-Extra: mlp
Requires-Dist: matgl>=1.2.7; python_version < "3.13" and extra == "mlp"
Provides-Extra: numba
Requires-Dist: numba>=0.55; extra == "numba"
Provides-Extra: numpy-v1
Requires-Dist: numpy<2,>=1.25.0; extra == "numpy-v1"
Provides-Extra: optional
Requires-Dist: pymatgen[abinit,ase,matcalc,mlp,tblite,zeopp]; extra == "optional"
Requires-Dist: beautifulsoup4; extra == "optional"
Requires-Dist: pymatgen-analysis-alloys; extra == "optional"
Requires-Dist: chemview>=0.6; extra == "optional"
Requires-Dist: f90nml>=1.1.2; extra == "optional"
Requires-Dist: galore>=0.6.1; extra == "optional"
Requires-Dist: h5py>=3.11.0; extra == "optional"
Requires-Dist: hiphive>=1.3.1; extra == "optional"
Requires-Dist: jarvis-tools>=2020.7.14; extra == "optional"
Requires-Dist: phonopy>=2.33.3; extra == "optional"
Requires-Dist: seekpath>=2.0.1; extra == "optional"
Provides-Extra: prototypes
Requires-Dist: pyxtal>=1.0; extra == "prototypes"
Requires-Dist: pymatgen[symmetry]; extra == "prototypes"
Provides-Extra: symmetry
Requires-Dist: moyopy[interface]>=0.3; extra == "symmetry"
Requires-Dist: spglib>=2.5; extra == "symmetry"
Provides-Extra: tblite
Requires-Dist: tblite[ase]>=0.3.0; (platform_system == "Linux" and python_version < "3.12") and extra == "tblite"
Provides-Extra: vis
Requires-Dist: vtk>=6.0.0; extra == "vis"
Provides-Extra: zeopp
Requires-Dist: pyzeo; platform_system != "Windows" and extra == "zeopp"
Dynamic: license-file
